Workbook

Sheet Assumptions
B1: 2024
A2: EBIT | B2: 1233490000
A3: Cash | B3: 1670273000
A4: Minority holdings | B4: 0
A5: Minority interest | B5: 164000
A7: Price per share ( 1 July 2024) | B7: 81.93
A8: # of shares | B8: 588090000
A9: Market value of debt | B9: 2174150000
A11: Market risk premium | B11: 0.055
B13: initial | C13: Terminal
A14: Tax rate | B14: 0.0521 | C14: 0.21
A15: Risk-free interest rate | B15: 0.0446 | C15: 0.0446
A16: Levered beta | B16: 1.36 | C16: 1
A17: Default Spread | B17: 0.0045 | C17: 0.0045
A18: ROA | B18: 0.1708 | C18: 0.1
A19: Reinvestment rate | B19: 0.1414 | C19: 0.05
A20: EBIT growth rate | B20: =B18 *B19 -> 0.02415112 | C20: 0.025

Sheet WACC
A1: Market capitalization | B1: =Assumptions!B7 * Assumptions!B8 -> 48182213700
A2: Market value of debt | B2: 2174150000
A4: Market risk premium | B4: =Assumptions!B11 -> 0.055
B6: Initial | C6: Terminal
A7: Risk-free interest rate | B7: =Assumptions!B15 -> 0.0446 | C7: =Assumptions!C15 -> 0.0446
A8: Unlevered beta (bottom-up) | B8: 1
A9: Levered beta | B9: =Assumptions!B16 -> 1.36 | C9: =Assumptions!C16 -> 1
A10: ke | B10: =$B7+B9*$B4 -> 0.1194 | C10: =$B7+C9*$B4 -> 0.0996
A12: Default Spread | B12: =Assumptions!B17 -> 0.0045 | C12: =Assumptions!C17 -> 0.0045
A13: kd | B13: =B7+B12 -> 0.0491 | C13: =C7+C12 -> 0.0491
A14: Tax rate | B14: =Assumptions!B14 -> 0.0521 | C14: =Assumptions!C14 -> 0.21
A15: kd(1-T) | B15: =B13*(1-B14) -> 0.04654189 | C15: =C13*(1-C14) -> 0.038789
B17: Value | C17: Weight
A18: Debt | B18: =Assumptions!B9 -> 2174150000 | C18: =B18/(B18+B19) -> 0.043175278 | D18: =B15 -> 0.04654189
A19: Equity | B19: =B1 -> 48182213700 | C19: =1-C18 -> 0.95682472 | D19: =B10 -> 0.1194
A20: WACC initial | D20: =SUMPRODUCT($C18:$C19,D18:D19) -> 0.11625433
C22: Weight
A23: Debt | C23: =C18 -> 0.043175278 | D23: =C15 -> 0.038789
A24: Equity | C24: =1-C18 -> 0.95682472 | D24: =C10 -> 0.0996
A25: WACC terminal | D25: =SUMPRODUCT($C18:$C19,D23:D24) -> 0.096974468

Sheet DCF
B1: 2024 | C1: 2025 | D1: 2026 | E1: 2027 | F1: 2028 | G1: 2029 | H1: Terminal
A2: EBIT | B2: =Assumptions!B2 -> 1233490000 | C2: =B2*(1+C12) -> 1263280165 | D2: =C2*(1+D12) -> 1293789796 | E2: =D2*(1+E12) -> 1325036268 | F2: =E2*(1+F12) -> 1357037378 | G2: =F2*(1+G12) -> 1389811351 | H2: =H3/(1-H11) -> 1544836175
A3: EBIT(1-T) | B3: =B2*(1-C11) -> 1169225171 | C3: =C2*(1-C11) -> 1197463268 | D3: =D2*(1-D11) -> 1226383348 | E3: =E2*(1-E11) -> 1256001879 | F3: =F2*(1-F11) -> 1286335731 | G3: =G2*(1-G11) -> 1317402180 | H3: =H5/(1-H13) -> 1220420578
A4: Reinvestment | C4: =C3*C13 -> 1.6932131e+08 | D4: =D3*D13 -> 1.7341061e+08 | E4: =E3*E13 -> 1.7759867e+08 | F4: =F3*F13 -> 1.8188787e+08 | G4: =G3*G13 -> 1.8628067e+08 | H4: =H3 * H13 -> 61021029
A5: FCFF | C5: =C3-C4 -> 1028141962 | D5: =D3-D4 -> 1052972742 | E5: =E3-E4 -> 1078403213 | F5: =F3-F4 -> 1104447859 | G5: =G3-G4 -> 1131121511 | H5: =G5*(1+H12) -> 1159399549
A7: Cot of capital | C7: =WACC!D20 -> 0.11625433 | D7: =C7 -> 0.11625433 | E7: =D7 -> 0.11625433 | F7: =E7 -> 0.11625433 | G7: =F7 -> 0.11625433 | H7: =WACC!D25 -> 0.096974468
A8: Discount factor | C8: =1/(1+C7) -> 0.89585319 | D8: =C8*1/(1+D7) -> 0.80255293 | E8: =D8*1/(1+E7) -> 0.7189696 | F8: =E8*1/(1+F7) -> 0.64409121 | G8: =F8*1/(1+G7) -> 0.57701116
A9: PV (FCFF) | C9: =C5 * C8 -> 9.2106425e+08 | D9: =D5 * D8 -> 8.4506636e+08 | E9: =E5 * E8 -> 775339130 | F9: =F5 * F8 -> 7.1136516e+08 | G9: =G5 * G8 -> 6.5266974e+08
A11: Tax rate | C11: =Assumptions!B14 -> 0.0521 | D11: =C11 -> 0.0521 | E11: =D11 -> 0.0521 | F11: =E11 -> 0.0521 | G11: =F11 -> 0.0521 | H11: =Assumptions!C14 -> 0.21
A12: EBIT growth rate | C12: =Assumptions!$B$20 -> 0.02415112 | D12: =C12 -> 0.02415112 | E12: =D12 -> 0.02415112 | F12: =E12 -> 0.02415112 | G12: =F12 -> 0.02415112 | H12: 0.025
A13: Reinvestment rate | C13: =Assumptions!B19 -> 0.1414 | D13: =C13 -> 0.1414 | E13: =D13 -> 0.1414 | F13: =E13 -> 0.1414 | G13: =F13 -> 0.1414 | H13: =Assumptions!C19 -> 0.05
A14: ROIC(ROA) | C14: =Assumptions!$B$18 -> 0.1708 | D14: =C14 -> 0.1708 | E14: =D14 -> 0.1708 | F14: =E14 -> 0.1708 | G14: =F14 -> 0.1708 | H14: =Assumptions!C18 -> 0.1
A18: FCFF (terminal) | B18: =H5 -> 1159399549
A19: Cost of capital (terminal) | B19: =H7 -> 0.096974468
A20: Value (terminal) | B20: =B18/(B19-H12) -> 16108483725
A22: PV (Terminal value) | B22: =B20 /((1 + H7)^5) -> 10140796432
A23: PV (initial FCFF) | B23: =SUM(C9:G9) -> 3905504644
A24: EV | B24: =B22+B23 -> 14046301076
A25: Minority holdings | B25: 0
A26: Cash | B26: =Assumptions!B3 -> 1670273000
A27: Firm value | B27: =B24+B25+B26 -> 15716574076
A28: - Minorit interest | B28: =Assumptions!B5 -> 164000
A29: - Debt | B29: =Assumptions!B9 -> 2174150000
A30: Equity | B30: =B27-B28-B29 -> 13542260076
A31: Nº shares (m) | B31: =Assumptions!B8 -> 588090000
A32: Valur per share | B32: =B30/B31 -> 23.02753
A33: Price | B33: =Assumptions!B7 -> 81.93
A34: Price/Value | B34: =B33/B32 -> 3.5579153
D36: Terminal WACC
A37: Sensitivity analysis | C37: =B32 -> 23.02753 | D37: 0.06 | E37: 0.07 | F37: =B19 -> 0.096974468 | G37: 0.09 | H37: 0.1
B38: g | C38: 0.015 | D38: =((($G5 * (1 + C38) / (D37 - C38)) / (1 + D$37)^5) + B23 + B26 - B29 - B28) / B31 -> 38.202174 | E38: =((($G5 * (1 + C38) / (E37 - C38)) / (1 + E$37)^5) + B23 + B26 - B29 - B28) / B31 -> 31.091457 | F38: =((($G5 * (1 + C38) / (F37 - C38)) / (1 + F$37)^5) + B23 + B26 - B29 - B28) / B31 -> 20.776287 | G38: =((($G5 * (1 + C38) / (G37 - C38)) / (1 + G$37)^5) + B23 + B26 - B29 - B28) / B31 -> 22.701478 | H38: =((($G5 * (1 + C38) / (H37 - C38)) / (1 + H$37)^5) + B23 + B26 - B29 - B28) / B31 -> 20.04489
C39: 0.02 | D39: =((($G5 * (1 + C39) / (D37 - C39)) / (1 + D$37)^5) + B23 + B26 - B29 - B28) / B31 -> 42.434114 | E39: =((($G5 * (1 + C39) / (E37 - C39)) / (1 + E$37)^5) + B23 + B26 - B29 - B28) / B31 -> 33.759345 | F39: =((($G5 * (1 + C39) / (F37 - C39)) / (1 + F$37)^5) + B23 + B26 - B29 - B28) / B31 -> 21.828792 | G39: =((($G5 * (1 + C39) / (G37 - C39)) / (1 + G$37)^5) + B23 + B26 - B29 - B28) / B31 -> 23.999166 | H39: =((($G5 * (1 + C39) / (H37 - C39)) / (1 + H$37)^5) + B23 + B26 - B29 - B28) / B31 -> 21.010842
C40: 0.025 | D40: =((($G5 * (1 + C40) / (D37 - C40)) / (1 + D$37)^5) + B23 + B26 - B29 - B28) / B31 -> 47.87518 | E40: =((($G5 * (1 + C40) / (E37 - C40)) / (1 + E$37)^5) + B23 + B26 - B29 - B28) / B31 -> 37.020098 | F40: =((($G5 * (1 + C40) / (F37 - C40)) / (1 + F$37)^5) + B23 + B26 - B29 - B28) / B31 -> 23.02753 | G40: =((($G5 * (1 + C40) / (G37 - C40)) / (1 + G$37)^5) + B23 + B26 - B29 - B28) / B31 -> 25.496498 | H40: =((($G5 * (1 + C40) / (H37 - C40)) / (1 + H$37)^5) + B23 + B26 - B29 - B28) / B31 -> 22.105589
C41: 0.03 | D41: =((($G5 * (1 + C41) / (D37 - C41)) / (1 + D$37)^5) + B23 + B26 - B29 - B28) / B31 -> 55.129935 | E41: =((($G5 * (1 + C41) / (E37 - C41)) / (1 + E$37)^5) + B23 + B26 - B29 - B28) / B31 -> 41.096038 | F41: =((($G5 * (1 + C41) / (F37 - C41)) / (1 + F$37)^5) + B23 + B26 - B29 - B28) / B31 -> 24.405252 | G41: =((($G5 * (1 + C41) / (G37 - C41)) / (1 + G$37)^5) + B23 + B26 - B29 - B28) / B31 -> 27.243385 | H41: =((($G5 * (1 + C41) / (H37 - C41)) / (1 + H$37)^5) + B23 + B26 - B29 - B28) / B31 -> 23.356727
C42: 0.035 | D42: =((($G5 * (1 + C42) / (D37 - C42)) / (1 + D$37)^5) + B23 + B26 - B29 - B28) / B31 -> 65.286591 | E42: =((($G5 * (1 + C42) / (E37 - C42)) / (1 + E$37)^5) + B23 + B26 - B29 - B28) / B31 -> 46.336534 | F42: =((($G5 * (1 + C42) / (F37 - C42)) / (1 + F$37)^5) + B23 + B26 - B29 - B28) / B31 -> 26.005279 | G42: =((($G5 * (1 + C42) / (G37 - C42)) / (1 + G$37)^5) + B23 + B26 - B29 - B28) / B31 -> 29.307888 | H42: =((($G5 * (1 + C42) / (H37 - C42)) / (1 + H$37)^5) + B23 + B26 - B29 - B28) / B31 -> 24.800349

Sheet Relative valuation
A1: Companies | B1: share price($) close of day 16th May 2025 | C1: # shares(m) | D1: debt($m) | E1: equity($m) | F1: EBIT($M) | G1: EBITDA($m) | H1: net income($m)
A2: Supermicro | B2: 46.15 | C2: 596.82 | D2: 2650 | E2: 5417 | F2: 1328 | G2: 1380 | H2: 1150
A3: HP | B3: 17.75 | C3: 1310 | D3: 17920 | E3: 24880 | F3: 2420 | G3: 4926 | H3: 2760
A4: DELL | B4: 114.19 | C4: 344.35 | D4: 25370 | E4: -1387 | F4: 6462 | G4: 9585 | H4: 4590
A5: Lenovo | B5: 25.27 | C5: 620.23 | D5: 3980 | E5: 6081 | F5: 2338 | G5: 3766 | H5: 1540
A6: Cisco | B6: 63.62 | C6: 3980 | D6: 29280 | E6: 45457 | F6: 11380 | G6: 14616 | H6: 9790
A8: Company | B8: Forward PE ratio | C8: EV/EBITDA | D8: PBV | E8: PEG ratio
A9: Supermicro | B9: 13.57 | C9: 19.93 | D9: 4.32 | E9: 0.76
A10: HP | B10: 9.44 | C10: 5.64 | D10: 1.12 | E10: 4.55
A11: DELL | B11: 12.25 | C11: 10.5 | D11: -53.4 | E11: 0.88
A12: Lenovo | B12: 9.15 | C12: 4.17 | D12: 2.85 | E12: 0.56
A13: Cisco | B13: 16 | C13: 17.7 | D13: 5.54 | E13: 2.13
A14: Avergae | B14: 11.71 | C14: 9.5 | D14: -10.97 | E14: 2.03
A15: Median | B15: 10.85 | C15: 8.07 | D15: 1.99 | E15: 1.51
A17: SMCI share value
A18: according to: | B18: PE | C18: EV/EBITDA | D18: PBV
A19: Average | B19: 22.56 | C19: 17.53 | D19: -99.59
A20: Median | B20: 20.9 | C20: 14.22 | D20: 18.02

Sheet Financial analysis
A1: (1000 USD$) | B1: 2024 | C1: 2023 | D1: 2022 | E1: 2021 | F1: 2020
A2: Net income | B2: 1152666 | C2: 639998 | D2: 285163 | E2: 111865 | F2: 84308
B4: 2024 | C4: 2023 | D4: 2022 | E4: 2021 | F4: 2020
A5: Gross margin (%) | B5: 14.03 | C5: 18.5 | D5: 16.02 | E5: 15.82 | F5: 16.61
A7: Balance sheet | B7: 2024 | C7: 2023 | D7: 2022 | E7: 2021 | F7: 2020
A8: Non Current assets | B8: 894132 | C8: 495303 | D8: 398762 | E8: 374705 | F8: 325885
A9: Current assets | B9: 8931960 | C9: 3179426 | D9: 2806315 | E9: 1867259 | F9: 1592761
A10: Shareholders funds | B10: 5417206 | C10: 1972005 | D10: 1425575 | E10: 1096225 | F10: 1065540
A11: Non Current liabilities | B11: 2063165 | C11: 328072 | D11: 309478 | E11: 176843 | F11: 145471
A12: Current liabilities | B12: 2345721 | C12: 1374652 | D12: 1470024 | E12: 968896 | F12: 707635
A13: Total | B13: 9826092 | C13: 3674729 | D13: 3205077 | E13: 2241964 | F13: 1918646
